umnet_napalm/__init__.py
umnet_napalm/abstract_base.py
umnet_napalm/asa/__init__.py
umnet_napalm/asa/asa.py
umnet_napalm/asa/utils/textfsm_templates/dhcprelay.tpl
umnet_napalm/asa/utils/textfsm_templates/sh_arp.tpl
umnet_napalm/asa/utils/textfsm_templates/sh_interface_detail.tpl
umnet_napalm/asa/utils/textfsm_templates/sh_route.tpl
umnet_napalm/base.py
umnet_napalm/cli/umnet_napalm_get.py
umnet_napalm/ios/__init__.py
umnet_napalm/ios/ios.py
umnet_napalm/ios/utils/textfsm_templates/sh_bgp_vpnv4_unicast_all_labels.tpl
umnet_napalm/ios/utils/textfsm_templates/sh_etherchannel_detail.tpl
umnet_napalm/ios/utils/textfsm_templates/sh_etherchannel_summary.tpl
umnet_napalm/ios/utils/textfsm_templates/sh_interface_description.tpl
umnet_napalm/ios/utils/textfsm_templates/sh_inventory.tpl
umnet_napalm/ios/utils/textfsm_templates/sh_ip_interface.tpl
umnet_napalm/ios/utils/textfsm_templates/sh_ip_route_vrf_all.tpl
umnet_napalm/ios/utils/textfsm_templates/sh_ipv6_interface.tpl
umnet_napalm/ios/utils/textfsm_templates/sh_mpls_forwarding_table.tpl
umnet_napalm/ios/utils/textfsm_templates/sh_power_inline.tpl
umnet_napalm/iosxr/__init__.py
umnet_napalm/iosxr/iosxr.py
umnet_napalm/iosxr/utils/textfsm_templates/sh_arp.tpl
umnet_napalm/iosxr/utils/textfsm_templates/sh_bundle.tpl
umnet_napalm/iosxr/utils/textfsm_templates/sh_interface_description.tpl
umnet_napalm/iosxr/utils/textfsm_templates/sh_inventory.tpl
umnet_napalm/iosxr/utils/textfsm_templates/sh_ip_interface.tpl
umnet_napalm/iosxr/utils/textfsm_templates/sh_ipv6_interface.tpl
umnet_napalm/iosxr/utils/textfsm_templates/sh_lacp.tpl
umnet_napalm/iosxr/utils/textfsm_templates/sh_lldp_neighbors_detail.tpl
umnet_napalm/iosxr/utils/textfsm_templates/sh_route.tpl
umnet_napalm/iosxr_netconf/__init__.py
umnet_napalm/iosxr_netconf/constants.py
umnet_napalm/iosxr_netconf/iosxr_netconf.py
umnet_napalm/junos/__init__.py
umnet_napalm/junos/junos.py
umnet_napalm/junos/junos_views.py
umnet_napalm/junos/junos_views.yml
umnet_napalm/models.py
umnet_napalm-1.2.3.dist-info/METADATA
umnet_napalm-1.2.3.dist-info/WHEEL
umnet_napalm-1.2.3.dist-info/entry_points.txt
umnet_napalm-1.2.3.dist-info/RECORD
