Metadata-Version: 2.3
Name: umnet-napalm
Version: 1.2.3
Summary: A custom version of NAPALM for UMnet
Author: Amy Liebowitz
Author-email: amylieb@umich.edu
Requires-Python: >=3.9,<4.0
Classifier: Programming Language :: Python :: 3
Classifier: Programming Language :: Python :: 3.9
Classifier: Programming Language :: Python :: 3.10
Classifier: Programming Language :: Python :: 3.11
Classifier: Programming Language :: Python :: 3.12
Classifier: Programming Language :: Python :: 3.13
Requires-Dist: napalm (==5.1.0)
Requires-Dist: pan-python (>=0.25.0,<0.26.0)
Requires-Dist: xmltodict (>=0.14.2,<0.15.0)
